strangeworks_braket/__init__.py
strangeworks_braket/device.py
strangeworks_braket/job.py
strangeworks_braket/task.py
strangeworks_braket/utils/ahs_utils.py
strangeworks_braket/utils/serializer.py
strangeworks_braket-1.0.22.dist-info/LICENSE
strangeworks_braket-1.0.22.dist-info/METADATA
strangeworks_braket-1.0.22.dist-info/WHEEL
strangeworks_braket-1.0.22.dist-info/RECORD
