Metadata-Version: 2.3
Name: strangeworks-braket
Version: 1.0.22
Summary: Strangeworks Braket SDK extension
License: Apache-2.0
Author: Strange Devs
Author-email: hello@strangeworks.com
Requires-Python: >=3.10,<4.0
Classifier: License :: OSI Approved :: Apache Software License
Classifier: Programming Language :: Python :: 3
Classifier: Programming Language :: Python :: 3.10
Classifier: Programming Language :: Python :: 3.11
Classifier: Programming Language :: Python :: 3.12
Classifier: Programming Language :: Python :: 3.13
Requires-Dist: amazon-braket-sdk (>=1.99.0,<2.0.0)
Requires-Dist: python-jose (==3.3.0)
Requires-Dist: strangeworks (>=0.7.4,<0.8.0)
